beams/__init__.py
beams/_version.py
beams/beam.py
beams/shapes.py
beams/utils.py
beams-0.1.0.dist-info/LICENSE
beams-0.1.0.dist-info/METADATA
beams-0.1.0.dist-info/WHEEL
beams-0.1.0.dist-info/top_level.txt
beams-0.1.0.dist-info/RECORD
